milankalkenings/__init__.py
milankalkenings/data_handling.py
milankalkenings/modules.py
milankalkenings/train_test.py
milankalkenings/utils.py
milankalkenings/visualization.py
milankalkenings-0.1.43.dist-info/LICENSE
milankalkenings-0.1.43.dist-info/METADATA
milankalkenings-0.1.43.dist-info/WHEEL
milankalkenings-0.1.43.dist-info/top_level.txt
milankalkenings-0.1.43.dist-info/RECORD
