Metadata-Version: 2.1
Name: milankalkenings
Version: 0.1.43
Summary: basic deep learning functionalities
Author: Milan Kalkenings
Author-email: milankalkenings@outlook.com
Classifier: Programming Language :: Python :: 3
Classifier: License :: OSI Approved :: MIT License
Classifier: Operating System :: OS Independent
Requires-Python: >=3.6
License-File: LICENSE
